LICENSE
README.md
setup.py
NlpToolkit_WordToVec.egg-info/PKG-INFO
NlpToolkit_WordToVec.egg-info/SOURCES.txt
NlpToolkit_WordToVec.egg-info/dependency_links.txt
NlpToolkit_WordToVec.egg-info/requires.txt
NlpToolkit_WordToVec.egg-info/top_level.txt
WordToVec/Iteration.py
WordToVec/NeuralNetwork.py
WordToVec/Vocabulary.py
WordToVec/VocabularyWord.py
WordToVec/WordToVecParameter.py
WordToVec/__init__.py