Metadata-Version: 2.1
Name: NlpToolkit-WordToVec
Version: 1.0.6
Summary: Word2Vec Library
Home-page: https://github.com/StarlangSoftware/WordToVec-Py
Author: olcay
Author-email: olcay.yildiz@ozyegin.edu.tr
License: UNKNOWN
Platform: UNKNOWN
License-File: LICENSE
